query_everywhere/__init__.py
query_everywhere/queryer.py
query_everywhere-0.1.10.dist-info/LICENSE
query_everywhere-0.1.10.dist-info/METADATA
query_everywhere-0.1.10.dist-info/WHEEL
query_everywhere-0.1.10.dist-info/RECORD
