Metadata-Version: 2.1
Name: query-everywhere
Version: 0.1.10
Summary: Query every resource in RDBMS for REST
Author: -LAN-
Author-email: laipz8200@outlook.com
Requires-Python: >=3.11,<4.0
Classifier: Programming Language :: Python :: 3
Classifier: Programming Language :: Python :: 3.11
Requires-Dist: sqlalchemy (>=2.0.19,<3.0.0)
